[
  {
    "author": "Daniel Roe",
    "description": "A site to toggle your developer mode on and off with ONE CLICK!",
    "title": "https://dev-mode.dev",
    "url": "https://dev-mode.dev/"
  },
  {
    "author": "Penpot",
    "description": "Penpot is the web-based open-source design tool that bridges the gap between designers and developers",
    "title": "Penpot",
    "url": "https://penpot.app/"
  },
  {
    "author": "Reddit /u/f8computer",
    "description": "Domain Registration",
    "title": "Registation",
    "url": "https://devmodepro.com/"
  },
  {
    "author": "Reddit /u/Mustang-22",
    "description": "Domain Registration",
    "title": "Registation",
    "url": "https://devmode.ca/"
  }
]
